hoomanmltk/__init__.py
hoomanmltk/nlp.py
hoomanmltk-0.1.0.dist-info/licenses/LICENSE
hoomanmltk-0.1.0.dist-info/METADATA
hoomanmltk-0.1.0.dist-info/WHEEL
hoomanmltk-0.1.0.dist-info/top_level.txt
hoomanmltk-0.1.0.dist-info/RECORD
